dynamo_pandas/__init__.py
dynamo_pandas/dynamo_pandas.py
dynamo_pandas/serde/__init__.py
dynamo_pandas/serde/serde.py
dynamo_pandas/transactions/__init__.py
dynamo_pandas/transactions/transactions.py
dynamo_pandas-1.4.0.dist-info/LICENSE
dynamo_pandas-1.4.0.dist-info/METADATA
dynamo_pandas-1.4.0.dist-info/WHEEL
dynamo_pandas-1.4.0.dist-info/top_level.txt
dynamo_pandas-1.4.0.dist-info/RECORD
