Metadata-Version: 2.1
Name: dynamo-pandas
Version: 1.4.0
Summary: Make working with pandas dataframe and AWS DynamoDB easy.
Home-page: https://github.com/DrGFreeman/dynamo-pandas
Author: Julien de la Bruère-Terreault
Author-email: drgfreeman@tuta.io
Maintainer: Julien de la Bruère-Terreault
Maintainer-email: drgfreeman@tuta.io
License: MIT
Classifier: Development Status :: 5 - Production/Stable
Classifier: License :: OSI Approved :: MIT License
Classifier: Programming Language :: Python :: 3
Classifier: Programming Language :: Python :: 3.9
Classifier: Programming Language :: Python :: 3.10
Classifier: Programming Language :: Python :: 3.11
Classifier: Programming Language :: Python :: 3.12
Classifier: Programming Language :: Python :: 3.13
Requires-Python: >=3.9
License-File: LICENSE
Requires-Dist: pandas >=1.2
Provides-Extra: boto3
Requires-Dist: boto3 ; extra == 'boto3'
